keep_alive/__init__.py
keep_alive/run.py
keep_screen_alive-0.0.5.dist-info/METADATA
keep_screen_alive-0.0.5.dist-info/WHEEL
keep_screen_alive-0.0.5.dist-info/entry_points.txt
keep_screen_alive-0.0.5.dist-info/RECORD
