Metadata-Version: 2.1
Name: keep-screen-alive
Version: 0.0.5
Summary: A thin wrapper around macos caffeinate to use a relative datetime
License: MIT
Author: Tim Willis
Requires-Python: >=3.11,<4.0
Classifier: Development Status :: 4 - Beta
Classifier: Environment :: Console
Classifier: Environment :: MacOS X
Classifier: Intended Audience :: Developers
Classifier: License :: OSI Approved :: MIT License
Classifier: Operating System :: MacOS
Classifier: Operating System :: MacOS :: MacOS X
Classifier: Programming Language :: Python :: 3
Classifier: Programming Language :: Python :: 3.11
Classifier: Programming Language :: Python :: 3.12
Requires-Dist: dateparser (>=1.1.8,<2.0.0)
Requires-Dist: six (>=1.16.0,<2.0.0)
